{
  "risk_register": {
    "program": "Generic Program Template",
    "version": "1.0.0",
    "methodology": "CVaR (Conditional Value at Risk)",
    "alpha_level": 0.95,
    "last_updated": "2024-09-05",
    
    "risk_categories": [
      {
        "category": "Technical",
        "cvar_threshold": 0.10,
        "status": "TEMPLATE",
        "description": "Technology development and implementation risks"
      },
      {
        "category": "Schedule", 
        "cvar_threshold": 0.05,
        "status": "TEMPLATE",
        "description": "Timeline and milestone delivery risks"
      },
      {
        "category": "Financial",
        "cvar_threshold": 0.08,
        "status": "TEMPLATE", 
        "description": "Budget and cost management risks"
      },
      {
        "category": "Safety",
        "cvar_threshold": 0.01,
        "status": "TEMPLATE",
        "description": "Safety and regulatory compliance risks"
      },
      {
        "category": "Operational",
        "cvar_threshold": 0.12,
        "status": "TEMPLATE",
        "description": "Operational and resource management risks"
      }
    ],
    
    "risk_assessment_framework": {
      "probability_scale": [1, 2, 3, 4, 5],
      "impact_scale": [1, 2, 3, 4, 5],
      "risk_appetite": {
        "low": "Risk score 1-8",
        "medium": "Risk score 9-15", 
        "high": "Risk score 16-25"
      }
    },
    
    "mitigation_strategies": {
      "avoid": "Eliminate risk source",
      "mitigate": "Reduce probability or impact",
      "transfer": "Share risk with third parties",
      "accept": "Accept residual risk"
    },
    
    "quantum_enhancements": {
      "enabled": true,
      "applications": [
        "Monte Carlo risk simulation",
        "Portfolio optimization under uncertainty",
        "Scenario analysis with quantum speedup"
      ]
    },
    
    "governance": {
      "review_frequency": "Monthly",
      "escalation_criteria": "CVaR thresholds exceeded",
      "approval_authority": "Risk Committee"
    }
  }
}